api_builder/__init__.py
api_builder/cloudformation.py
api_builder/configuration.py
api_builder/zlab.py
api_builder/static/api.yml
api_builder/static/bootstrap.yml
api_builder/static/endpoint.py
api_builder/static/lambda.yml
api_builder/subcommands/__init__.py
api_builder/subcommands/api.py
api_builder/subcommands/bootstrap.py
api_builder/subcommands/lambda.py
aws_lambda_api_builder-0.0.8.dist-info/METADATA
aws_lambda_api_builder-0.0.8.dist-info/RECORD
aws_lambda_api_builder-0.0.8.dist-info/WHEEL
aws_lambda_api_builder-0.0.8.dist-info/entry_points.txt
aws_lambda_api_builder-0.0.8.dist-info/top_level.txt
